MANIFEST.in
README.rst
setup.py
spenx/__init__.py
spenx/parser.py
spenx/version.py
spenx/visitor.py
spenx.egg-info/PKG-INFO
spenx.egg-info/SOURCES.txt
spenx.egg-info/dependency_links.txt
spenx.egg-info/requires.txt
spenx.egg-info/top_level.txt
spenx/ext/__init__.py
spenx/ext/jinja.py
spenx/ext/mako.py