Metadata-Version: 2.1
Name: spenx
Version: 1.0.0
Summary: Python 3 template parser to generate HTML from a pug/jade like syntax
Home-page: https://github.com/ducent/spenx
Author: Julien LEICHER
License: GPL-3.0
Platform: UNKNOWN
Classifier: Development Status :: 4 - Beta
Classifier: Intended Audience :: Developers
Classifier: License :: OSI Approved :: GNU Affero General Public License v3
Classifier: Operating System :: OS Independent
Classifier: Programming Language :: Python :: 3
Classifier: Topic :: Text Processing :: Markup
Provides-Extra: test
